distrib_sample/__init__.py
distrib_sample/randomfunc.py
distrib_sample/randomobj.py
distrib_sample-0.0.1.dist-info/LICENSE
distrib_sample-0.0.1.dist-info/METADATA
distrib_sample-0.0.1.dist-info/WHEEL
distrib_sample-0.0.1.dist-info/top_level.txt
distrib_sample-0.0.1.dist-info/RECORD
