Metadata-Version: 2.1
Name: distrib-sample
Version: 0.0.1
Summary: Package to draw random samples
Home-page: UNKNOWN
Author: Clar Ni Shealbhaigh
Author-email: author@example.com
License: UNKNOWN
Platform: UNKNOWN
Classifier: Programming Language :: Python :: 3
Classifier: License :: OSI Approved :: MIT License
Classifier: Operating System :: OS Independent
Requires-Python: >=3.6
